qonto_mcp_server/__init__.py
qonto_mcp_server/__main__.py
qonto_mcp_server/server.py
qonto_mcp_server/api/__init__.py
qonto_mcp_server/api/client.py
qonto_mcp_server/api/config.py
qonto_mcp_server/api/methods.py
qonto_mcp_server-0.1.4.dist-info/METADATA
qonto_mcp_server-0.1.4.dist-info/WHEEL
qonto_mcp_server-0.1.4.dist-info/entry_points.txt
qonto_mcp_server-0.1.4.dist-info/licenses/LICENSE
qonto_mcp_server-0.1.4.dist-info/RECORD
