Metadata-Version: 2.4
Name: qonto-mcp-server
Version: 0.1.4
Summary: MCP Server for the Qonto API.
Project-URL: Homepage, https://github.com/j-about/Qonto-MCP-Server
Project-URL: Issues, https://github.com/j-about/Qonto-MCP-Server/issues
Author-email: j-about <142051449+j-about@users.noreply.github.com>
License-Expression: MIT
License-File: LICENSE
Classifier: Development Status :: 4 - Beta
Classifier: Programming Language :: Python :: 3
Classifier: Programming Language :: Python :: 3 :: Only
Classifier: Programming Language :: Python :: 3.10
Classifier: Programming Language :: Python :: 3.11
Classifier: Programming Language :: Python :: 3.12
Classifier: Programming Language :: Python :: 3.13
Classifier: Topic :: Scientific/Engineering :: Artificial Intelligence
Classifier: Topic :: Software Development :: Libraries :: Python Modules
Requires-Python: >=3.10
Requires-Dist: httpx<1.0,>=0.28
Requires-Dist: mcp[cli]<2.0,>=1.8
